txt2csv/__init__.py
txt2csv/cli.py
txt2csv/functions.py
txt2csv/node.csv
txt2csv/node.lis
txt2csv/py.typed
txt2csv-0.1.0.dist-info/METADATA
txt2csv-0.1.0.dist-info/WHEEL
txt2csv-0.1.0.dist-info/entry_points.txt
txt2csv-0.1.0.dist-info/licenses/LICENSE
txt2csv-0.1.0.dist-info/RECORD
