Metadata-Version: 2.4
Name: txt2csv
Version: 0.1.0
Summary: A tool to find and convert tables in txt files to csv files
Author-email: philippe <philippe.qu@outlook.com>
License-File: LICENSE
Requires-Python: >=3.13
Requires-Dist: click>=8.2.0
Requires-Dist: pandas>=2.2.3
